setup.py
chestymetrics/__init__.py
chestymetrics.egg-info/PKG-INFO
chestymetrics.egg-info/SOURCES.txt
chestymetrics.egg-info/dependency_links.txt
chestymetrics.egg-info/entry_points.txt
chestymetrics.egg-info/top_level.txt
chestymetrics/lib/__init__.py
chestymetrics/lib/cassandra/__init__.py
chestymetrics/lib/cassandra/client.py
chestymetrics/lib/collector/__init__.py
chestymetrics/lib/collector/collector.py
chestymetrics/lib/collector/cpu.py
chestymetrics/lib/collector/disk.py
chestymetrics/lib/collector/memory.py
chestymetrics/lib/collector/network.py
chestymetrics/lib/config/__init__.py
chestymetrics/lib/config/config.py
chestymetrics/lib/consumer/__init__.py
chestymetrics/lib/consumer/consumer.py
chestymetrics/lib/logger/__init__.py
chestymetrics/lib/logger/logger.py
chestymetrics/lib/rabbitmq/__init__.py
chestymetrics/lib/rabbitmq/client.py
chestymetrics/lib/rabbitmq/message.py
chestymetrics/lib/riemann/__init__.py
chestymetrics/lib/riemann/client.py