Metadata-Version: 1.1
Name: chestymetrics
Version: 0.0.6
Summary: foo
Home-page: http://www.google.com
Author: max
Author-email: max@max.com
License: GPLv3
Platform: UNKNOWN
Requires: pika
Requires: click
Requires: psutil
Requires: cassandra_driver
Requires: riemann_client
Requires: python_systemd
